dd_datasets/__init__.py
dd_datasets/adapter.py
dd_datasets/base.py
dd_datasets/dataflow_builder.py
dd_datasets/info.py
dd_datasets/py.typed
dd_datasets/registry.py
dd_datasets/save.py
dd_datasets/instances/__init__.py
dd_datasets/instances/doclaynet.py
dd_datasets/instances/fintabnet.py
dd_datasets/instances/funsd.py
dd_datasets/instances/iiitar13k.py
dd_datasets/instances/layouttest.py
dd_datasets/instances/publaynet.py
dd_datasets/instances/pubtables1m.py
dd_datasets/instances/pubtabnet.py
dd_datasets/instances/rvlcdip.py
dd_datasets/instances/xfund.py
dd_datasets/instances/xsl/__init__.py
dd_datasets-1.0.6.dist-info/METADATA
dd_datasets-1.0.6.dist-info/WHEEL
dd_datasets-1.0.6.dist-info/top_level.txt
dd_datasets-1.0.6.dist-info/RECORD
